mylib_035/__init__.py
mylib_035-0.1.dist-info/LICENSE.txt
mylib_035-0.1.dist-info/METADATA
mylib_035-0.1.dist-info/WHEEL
mylib_035-0.1.dist-info/top_level.txt
mylib_035-0.1.dist-info/RECORD
