Metadata-Version: 2.1
Name: mylib-035
Version: 0.1
Summary: hiring info
Author: sahil_mate
Author-email: matesahil98@gmail.com
Classifier: Programming Language :: Python :: 3
Classifier: License :: OSI Approved :: MIT License
Classifier: Operating System :: OS Independent
License-File: LICENSE.txt
